isoprompt/__init__.py
isoprompt/__main__.py
isoprompt/cli.py
isoprompt/constants.py
isoprompt/domains.py
isoprompt/models.py
isoprompt/modes.py
isoprompt/optimizer.py
isoprompt/py.typed
isoprompt/templates.py
isoprompt-1.0.4.dist-info/licenses/LICENSE
isoprompt-1.0.4.dist-info/METADATA
isoprompt-1.0.4.dist-info/WHEEL
isoprompt-1.0.4.dist-info/entry_points.txt
isoprompt-1.0.4.dist-info/top_level.txt
isoprompt-1.0.4.dist-info/RECORD
